phylofisher/__init__.py
phylofisher/apply_to_db.py
phylofisher/build_dataset.py
phylofisher/config.py
phylofisher/fisher.py
phylofisher/fishing_net.py
phylofisher/forest.py
phylofisher/forge.py
phylofisher/help_formatter.py
phylofisher/informant.py
phylofisher/install_deps.py
phylofisher/lumberjack.py
phylofisher/matrix_constructor.py
phylofisher/missing_data.py
phylofisher/prep_final_dataset.py
phylofisher/purge.py
phylofisher/select_orthologs.py
phylofisher/select_taxa.py
phylofisher/sgt_constructor.py
phylofisher/single_gene_tree_constructor.py
phylofisher/subset_orthologs.py
phylofisher/subset_taxa.py
phylofisher/subset_tools.py
phylofisher/tools.py
phylofisher/working_dataset_constructor.py
phylofisher/utilities/SR4_class_recoder.py
phylofisher/utilities/__init__.py
phylofisher/utilities/aa_comp_calculator.py
phylofisher/utilities/astral_runner.py
phylofisher/utilities/backup_restoration.py
phylofisher/utilities/bipartition_examiner.py
phylofisher/utilities/build_database.py
phylofisher/utilities/explore_database.py
phylofisher/utilities/fast_site_removal.py
phylofisher/utilities/fast_site_remover.py
phylofisher/utilities/fast_tax_removal.py
phylofisher/utilities/fast_taxa_remover.py
phylofisher/utilities/genetic_code.py
phylofisher/utilities/genetic_code_examiner.py
phylofisher/utilities/heterotachy.py
phylofisher/utilities/mammal_modeler.py
phylofisher/utilities/missing_data.py
phylofisher/utilities/purge.py
phylofisher/utilities/random_resampler.py
phylofisher/utilities/random_sample_iteration.py
phylofisher/utilities/rtc_binner.py
phylofisher/utilities/taxon_collapser.py
phylofisher-1.1.1.data/scripts/SR4_class_recoder.py
phylofisher-1.1.1.data/scripts/aa_comp_calculator.py
phylofisher-1.1.1.data/scripts/apply_to_db.py
phylofisher-1.1.1.data/scripts/astral_runner.py
phylofisher-1.1.1.data/scripts/backup_restoration.py
phylofisher-1.1.1.data/scripts/bipartition_examiner.py
phylofisher-1.1.1.data/scripts/build_database.py
phylofisher-1.1.1.dist-info/LICENSE.txt
phylofisher-1.1.1.dist-info/METADATA
phylofisher-1.1.1.dist-info/WHEEL
phylofisher-1.1.1.dist-info/top_level.txt
phylofisher-1.1.1.dist-info/RECORD
