Metadata-Version: 2.1
Name: phylofisher
Version: 1.1.1
Summary: PhyloFisher is a software package for the creation, analysis, and visualization of phylogenomic datasets that consist of protein sequences from eukaryotic organisms.
Home-page: https://github.com/TheBrownLab/PhyloFisher
Author: David Zihala
Author-email: zihaladavid@gmail.com
License: MIT
Platform: UNKNOWN
Requires-Python: ==3.7.10
License-File: LICENSE.txt
Requires-Dist: biopython (==1.78)
Requires-Dist: pyqt5 (==5.12.3)
Requires-Dist: ete3 (==3.1.2)
Requires-Dist: pandas (==1.2.4)
Requires-Dist: matplotlib (==3.4.1)
Requires-Dist: scipy (==1.6.2)
Requires-Dist: numpy (==1.21.0)
